icfg/__init__.py
icfg/_cfg.py
icfg-0.0.2.dist-info/LICENSE
icfg-0.0.2.dist-info/METADATA
icfg-0.0.2.dist-info/WHEEL
icfg-0.0.2.dist-info/top_level.txt
icfg-0.0.2.dist-info/RECORD
